README.rst
pyproject.toml
setup.py
src/bitex/__init__.py
src/bitex/adapter.py
src/bitex/auth.py
src/bitex/exceptions.py
src/bitex/plugins.py
src/bitex/request.py
src/bitex/response.py
src/bitex/session.py
src/bitex/types.py
src/bitex/constants/__init__.py
src/bitex/constants/private.py
src/bitex/constants/public.py
src/bitex_framework.egg-info/PKG-INFO
src/bitex_framework.egg-info/SOURCES.txt
src/bitex_framework.egg-info/dependency_links.txt
src/bitex_framework.egg-info/requires.txt
src/bitex_framework.egg-info/top_level.txt