Metadata-Version: 2.1
Name: bitex-framework
Version: 1.2.3
Summary: Core Module of the Bitcoin Exchange (BitEx) REST API Framwork
Home-page: https://github.com/crypto-toolbox/bitex-framework
Author: Nils Diefenbach
Author-email: nlsdfnbch.foss@kolabnow.com
License: UNKNOWN
Project-URL: Bug Reports, https://github.com/crypto-toolbox/bitex-framework/issues
Project-URL: Source, https://github.com/crypto-toolbox/bitex-framework
Keywords: bitcoin rest api http exchange
Platform: UNKNOWN
Classifier: Development Status :: 3 - Alpha
Classifier: Intended Audience :: Developers
Classifier: License :: OSI Approved :: MIT License
Classifier: Programming Language :: Python :: 3.6
Classifier: Programming Language :: Python :: 3.7
Classifier: Programming Language :: Python :: 3.8
Requires-Python: >=3.6, <4
Provides-Extra: ci
Provides-Extra: dev
Provides-Extra: test
